pyworks_orm/__init__.py
pyworks_orm/orator/__init__.py
pyworks_orm/orator/commands/__init__.py
pyworks_orm/orator/commands/application.py
pyworks_orm/orator/commands/command.py
pyworks_orm/orator/commands/migrations/__init__.py
pyworks_orm/orator/commands/migrations/base_command.py
pyworks_orm/orator/commands/migrations/install_command.py
pyworks_orm/orator/commands/migrations/make_command.py
pyworks_orm/orator/commands/migrations/migrate_command.py
pyworks_orm/orator/commands/migrations/refresh_command.py
pyworks_orm/orator/commands/migrations/reset_command.py
pyworks_orm/orator/commands/migrations/rollback_command.py
pyworks_orm/orator/commands/migrations/status_command.py
pyworks_orm/orator/commands/models/__init__.py
pyworks_orm/orator/commands/models/make_command.py
pyworks_orm/orator/commands/models/stubs.py
pyworks_orm/orator/commands/seeds/__init__.py
pyworks_orm/orator/commands/seeds/base_command.py
pyworks_orm/orator/commands/seeds/make_command.py
pyworks_orm/orator/commands/seeds/seed_command.py
pyworks_orm/orator/connections/__init__.py
pyworks_orm/orator/connections/connection.py
pyworks_orm/orator/connections/connection_interface.py
pyworks_orm/orator/connections/connection_resolver_interface.py
pyworks_orm/orator/connections/mysql_connection.py
pyworks_orm/orator/connections/postgres_connection.py
pyworks_orm/orator/connections/sqlite_connection.py
pyworks_orm/orator/connectors/__init__.py
pyworks_orm/orator/connectors/connection_factory.py
pyworks_orm/orator/connectors/connector.py
pyworks_orm/orator/connectors/mysql_connector.py
pyworks_orm/orator/connectors/postgres_connector.py
pyworks_orm/orator/connectors/sqlite_connector.py
pyworks_orm/orator/database_manager.py
pyworks_orm/orator/dbal/__init__.py
pyworks_orm/orator/dbal/abstract_asset.py
pyworks_orm/orator/dbal/column.py
pyworks_orm/orator/dbal/column_diff.py
pyworks_orm/orator/dbal/comparator.py
pyworks_orm/orator/dbal/exceptions/__init__.py
pyworks_orm/orator/dbal/foreign_key_constraint.py
pyworks_orm-1.0.0a1.dist-info/entry_points.txt
pyworks_orm-1.0.0a1.dist-info/LICENSE
pyworks_orm-1.0.0a1.dist-info/WHEEL
pyworks_orm-1.0.0a1.dist-info/METADATA
pyworks_orm-1.0.0a1.dist-info/RECORD
